aliyunsdkddosbgp/__init__.py
aliyunsdkddosbgp/endpoint.py
aliyunsdkddosbgp/request/__init__.py
aliyunsdkddosbgp/request/v20180720/AddIpRequest.py
aliyunsdkddosbgp/request/v20180720/CheckAccessLogAuthRequest.py
aliyunsdkddosbgp/request/v20180720/CheckGrantRequest.py
aliyunsdkddosbgp/request/v20180720/ConfigSchedruleOnDemandRequest.py
aliyunsdkddosbgp/request/v20180720/CreateSchedruleOnDemandRequest.py
aliyunsdkddosbgp/request/v20180720/DeleteBlackholeRequest.py
aliyunsdkddosbgp/request/v20180720/DeleteIpRequest.py
aliyunsdkddosbgp/request/v20180720/DeleteSchedruleOnDemandRequest.py
aliyunsdkddosbgp/request/v20180720/DescribeDdosEventRequest.py
aliyunsdkddosbgp/request/v20180720/DescribeExcpetionCountRequest.py
aliyunsdkddosbgp/request/v20180720/DescribeInstanceListRequest.py
aliyunsdkddosbgp/request/v20180720/DescribeInstanceSpecsRequest.py
aliyunsdkddosbgp/request/v20180720/DescribeOnDemandDdosEventRequest.py
aliyunsdkddosbgp/request/v20180720/DescribeOnDemandInstanceStatusRequest.py
aliyunsdkddosbgp/request/v20180720/DescribeOpEntitiesRequest.py
aliyunsdkddosbgp/request/v20180720/DescribePackIpListRequest.py
aliyunsdkddosbgp/request/v20180720/DescribeRegionsRequest.py
aliyunsdkddosbgp/request/v20180720/DescribeTrafficRequest.py
aliyunsdkddosbgp/request/v20180720/GetSlsOpenStatusRequest.py
aliyunsdkddosbgp/request/v20180720/ListOpenedAccessLogInstancesRequest.py
aliyunsdkddosbgp/request/v20180720/ListTagKeysRequest.py
aliyunsdkddosbgp/request/v20180720/ListTagResourcesRequest.py
aliyunsdkddosbgp/request/v20180720/ModifyRemarkRequest.py
aliyunsdkddosbgp/request/v20180720/QuerySchedruleOnDemandRequest.py
aliyunsdkddosbgp/request/v20180720/SetInstanceModeOnDemandRequest.py
aliyunsdkddosbgp/request/v20180720/TagResourcesRequest.py
aliyunsdkddosbgp/request/v20180720/UntagResourcesRequest.py
aliyunsdkddosbgp/request/v20180720/__init__.py
aliyun_python_sdk_ddosbgp-1.0.1.dist-info/LICENSE
aliyun_python_sdk_ddosbgp-1.0.1.dist-info/METADATA
aliyun_python_sdk_ddosbgp-1.0.1.dist-info/WHEEL
aliyun_python_sdk_ddosbgp-1.0.1.dist-info/top_level.txt
aliyun_python_sdk_ddosbgp-1.0.1.dist-info/RECORD
